{
    "bio_url": "https://www.nexusmods.com/skyrimspecialedition/mods/94808",
    "bio": "FjorStaag Fire-Eater (Nord Male): In the cold embrace of Windhelm, my Nord blood was steeled in the fires of combat. My ability to devour flames earned me a name. Now, as the Dragonborn rises, I bring both my fiery breath and martial skill to their side.",
    "name": "FjorStaag Fire-Eater",
    "voice_model": "MaleNord",
    "voice_folder": "MaleNord",
    "race": "Nord",
    "gender": "Male",
    "species": "Human",
    "ref_id": "55B",
    "base_id": null,
    "lang_override": "",
    "behavior_blacklist": [],
    "behavior_whitelist": [],
    "notes": null
}