{
    "bio_url": "/wiki/Usha",
    "bio": "Usha is a deceased Argonian found on Solstheim in a hidden camp area near the headwaters of the stream that flows south, just west of Ashfallow Citadel.\r\nOn the table next to him is Letter to Usha, which gives some insight into his background. Also on the table are three skooma bottles, and scattered around his corpse are a number of empty ones.\r\nA plate, which was likely used as a gold pan, can be found near the stream of water. Various pieces of Gold Ore are found right next to it on the table.",
    "name": "Usha",
    "voice_model": "MaleArgonian",
    "skyrim_voice_folder": "MaleArgonian",
    "race": "Argonian",
    "gender": "Male",
    "species": "Argonian",
    "ref_id": "035371",
    "base_id": "03537E",
    "lang_override": "",
    "behavior_blacklist": [],
    "behavior_whitelist": [],
    "notes": "Deceased - Probably not interactable"
}