{
    "bio_url": "/wiki/Karl",
    "bio": "Karl is an elderly Nord miner found in Dawnstar. He is involved with a Miscellaneous Quest which can lead to the Thane title being given to the Dragonborn.\r\nKarl can be found working the Smelter\u00a0at the Iron-Breaker Mine, and drinking outside the Windpeak Inn at night.\r\nLike all drunks, Karl can be given an alcoholic beverage, in which he will act positively towards the Dragonborn afterward.\r\nBeitild: \"Keep at it. We need to work twice as hard now that fat-headed Leigelf has declared war!\" Karl: \"We're at war with Leigelf? Isn't he your husband?\" Karl: \"Drafted into a war, how could my life get worse?\"",
    "name": "Karl",
    "voice_model": "MaleDrunk",
    "skyrim_voice_folder": "MaleDrunk",
    "race": "Nord",
    "gender": "Male",
    "species": "Human",
    "ref_id": "01A6BC",
    "base_id": "013619",
    "lang_override": "",
    "behavior_blacklist": [],
    "behavior_whitelist": [],
    "notes": null
}