{
    "bio_url": "https://www.nexusmods.com/skyrimspecialedition/mods/595",
    "bio": "Lulanne, a young Nord woman, lives in Windhelm and works as a barmaid at Candlehearth Hall, a popular inn/tavern near the center of the city. Candlehearth Hall is run by an older woman named Elda Early-Dawn. One of Lulanne's fellow barmaid coworkers is a young woman named Veronica. A woman named Lynette also works there as a barmaid, and additionally helps coordinate the renting of rooms at the inn.\r\nLulanne is tall (for a woman), and has long light brown hair and blue-green eyes. She wears a somewhat revealing barmaid outfit, typical of barmaids in Skyrim.",
    "name": "Lulanne",
    "voice_model": "FemaleYoungEager",
    "skyrim_voice_folder": "FemaleYoungEager",
    "race": "Nord",
    "gender": "Female",
    "species": "Human",
    "ref_id": "03191B",
    "base_id": "03191A",
    "lang_override": "",
    "behavior_blacklist": [],
    "behavior_whitelist": [],
    "notes": null
}