{
    "bio_url": "/wiki/Frothar",
    "bio": "Frothar is a Nord child and the eldest son of Balgruuf the Greater, and as such is in line to eventually succeed his father as the Jarl of Whiterun.\r\nHe can be usually be found walking around Dragonsreach, the jarl's palace in Whiterun. Frothar has a half-brother named Nelkir and a sister named Dagny.\r\nUnlike his siblings, he doesn't make any condescending comments towards visitors to the palace.",
    "name": "Frothar",
    "voice_model": "MaleChild",
    "skyrim_voice_folder": "MaleChild",
    "race": "Nord",
    "gender": "Male",
    "species": "Human",
    "ref_id": "01A679",
    "base_id": "01434C",
    "lang_override": "",
    "behavior_blacklist": [],
    "behavior_whitelist": [],
    "notes": "Shawn - started"
}