{
    "bio_url": "/wiki/Arvel_the_Swift",
    "bio": "Arvel the Swift is a Dunmer man who is trapped in a spider web at Bleak Falls Barrow. Arvel wears a full set of hide armor. He is carrying the Golden Claw, which he stole from Lucan Valerius in Riverwood.\r\nArvel is trapped in a spider's web, and he asks to be freed. \r\nQuotes:\r\n\u201cYes, the claw. I know how it works. The claw, the markings, the door in the Hall of Stories. I know how they all fit together! Help me down, and I'll show you. You won't believe the power the Nords have hidden there.\"",
    "name": "Arvel the Swift",
    "voice_model": "MaleDunmer",
    "skyrim_voice_folder": "MaleDarkElf",
    "race": "Dunmer",
    "gender": "Male",
    "species": "Elf",
    "ref_id": "039655",
    "base_id": "039646",
    "lang_override": "",
    "behavior_blacklist": [],
    "behavior_whitelist": [],
    "notes": "Shawn - done"
}