{
    "bio_url": "/wiki/Bashnag",
    "bio": "Bashnag, an Orc man, is spellsword who leads the group of necromancers inside Southfringe Sanctum.\r\nThe mages found in the sanctum are a group of necromancers that practice their school of magic in hiding. Bashnag recently put a curse on a conjurer named Selveni Nethri (a Dunmer woman) so that she could not cast any spells, and threw her in the spider's pit.\r\nIn combat, Bashnag will summon Frost Atronachs and use Frost and Shock spells. When out of Magicka, he will attack using his staff and mace. He wears Ancient Nord Armor.",
    "name": "Bashnag",
    "voice_model": "MaleOrc",
    "skyrim_voice_folder": "MaleOrc",
    "race": "Orsimer",
    "gender": "Male",
    "species": "Elf",
    "ref_id": "02B99D",
    "base_id": "0A33EA",
    "lang_override": "",
    "is_generic_npc": false,
    "behavior_blacklist": [],
    "behavior_whitelist": [],
    "notes": "Shawn - done"
}