{
    "bio_url": "https://www.nexusmods.com/skyrimspecialedition/mods/595",
    "bio": "Lielle lives in Markarth, where she works as a servant at Understone Keep. Understone Keep is an ancient Dwemer keep built into the mountainside, used as a palace by the jarl of Markarth. From Understone Keep, the jarl rules over Markarth and the rest of The Reach (of which Markarth is the capital).\r\nLielle is a young petite Breton woman with light blonde hair and striking blue eyes, She usually wears a somewhat revealing barmaid outfit. She spends most of her working hours serving food and drinks to the inhabitants of the keep, as well as to important visitors.\r\nQuotes:\r\n\"What can I do for you?\"\r\n\"Need something?\"",
    "name": "Lielle",
    "voice_model": "FemaleYoungEager",
    "skyrim_voice_folder": "FemaleYoungEager",
    "race": "Breton",
    "gender": "Female",
    "species": "Human",
    "ref_id": "013604",
    "base_id": "013601",
    "lang_override": "",
    "is_generic_npc": false,
    "behavior_blacklist": [],
    "behavior_whitelist": [],
    "notes": null
}