{
    "bio_url": "https://www.nexusmods.com/skyrimspecialedition/mods/1163",
    "bio": "I am Darion Fleetfoot, a bard who performs at the Winking Skeever in Solitude. I take pride in my music and love to entertain the patrons of the inn. However, I fear that my music might not be appreciated by everyone. My ultimate goal is to become the most famous bard in all of Skyrim and have my music heard by people all over Tamriel.",
    "name": "Darion Fleetfoot",
    "voice_model": "MaleCommander",
    "skyrim_voice_folder": "darionvoice",
    "race": "Altmer",
    "gender": "Male",
    "species": "Elf",
    "ref_id": "10E503",
    "base_id": "1101A3",
    "lang_override": "",
    "is_generic_npc": false,
    "behavior_blacklist": [],
    "behavior_whitelist": [],
    "notes": "Shawn - MaleCommander sounds kinda close, and has been assigned"
}